my_module.py
jove_test_module-0.1.dist-info/METADATA
jove_test_module-0.1.dist-info/WHEEL
jove_test_module-0.1.dist-info/top_level.txt
jove_test_module-0.1.dist-info/RECORD
